[
  {
    "name": "brandnew",
    "url": "gs://[object Object]/brandnew",
    "model": "68167302-85ec-4951-ba50-30af0c3c3190_model_adapter",
    "modelCreationTime": "2024-08-12T21:12:35.571Z"
  },
  {
    "name": "daj_bog_da_dela",
    "url": "gs://[object Object]/daj_bog_da_dela",
    "model": "b077e14c-935f-4ca5-9e3c-b6d63f77b3ce_model_adapter",
    "modelCreationTime": "2024-08-12T16:11:04.653Z"
  },
  {
    "name": "novadomena",
    "url": "gs://[object Object]/novadomena",
    "model": "",
    "modelCreationTime": ""
  },
  {
    "name": "seenadomena",
    "url": "gs://[object Object]/seenadomena",
    "model": "",
    "modelCreationTime": ""
  },
  {
    "name": "datascience",
    "url": "gs://[object Object]/datascience",
    "model": "68167302-85ec-4951-ba50-30af0c3c3190_model_adapter",
    "modelCreationTime": "2024-08-12T21:15:15.461Z"
  }
]